image2grid/__init__.py
image2grid/cli.py
image2grid/cropper.py
image2grid-0.1.1.dist-info/LICENSE
image2grid-0.1.1.dist-info/METADATA
image2grid-0.1.1.dist-info/WHEEL
image2grid-0.1.1.dist-info/entry_points.txt
image2grid-0.1.1.dist-info/RECORD
