Metadata-Version: 2.1
Name: image2grid
Version: 0.1.1
Summary: Turn an image into a grid images
Home-page: https://github.com/kiwamizamurai
License: MIT
Author: kiwamizamurai
Author-email: 24860100+kiwamizamurai@users.noreply.github.com
Requires-Python: >=3.10,<4.0
Classifier: License :: OSI Approved :: MIT License
Classifier: Programming Language :: Python :: 3
Classifier: Programming Language :: Python :: 3.10
Classifier: Programming Language :: Python :: 3.11
Classifier: Programming Language :: Python :: 3.12
Requires-Dist: gitpython (==3.1.43)
Requires-Dist: moviepy (==1.0.3)
Requires-Dist: pillow (==9.5.0)
Project-URL: Repository, https://github.com/kiwamizamurai/image2grid
